parselist/__init__.py
parselist/pl.py
parselist-0.0.1.dist-info/LICENSE
parselist-0.0.1.dist-info/METADATA
parselist-0.0.1.dist-info/WHEEL
parselist-0.0.1.dist-info/top_level.txt
parselist-0.0.1.dist-info/RECORD
